[{"deviceID": 0, "interactions": [{"duration": 1.3390120669782342, "start": "/Date(1511677623263)/"}]}, {"deviceID": 1, "interactions": [{"duration": 7.00971270598064, "start": "/Date(1511677623263)/"}]}, {"deviceID": 2, "interactions": [{"duration": 4.12308784580247, "start": "/Date(1511677623263)/"}]}, {"deviceID": 3, "interactions": [{"duration": 3.628249504274372, "start": "/Date(1511677623263)/"}]}, {"deviceID": 5, "interactions": [{"duration": 5.863264997264526, "start": "/Date(1511677623263)/"}]}, {"deviceID": 6, "interactions": [{"duration": 4.940604120987939, "start": "/Date(1511677623263)/"}]}, {"deviceID": 8, "interactions": [{"duration": 3.440654181985138, "start": "/Date(1511677623263)/"}]}, {"deviceID": 10, "interactions": [{"duration": 4.815576042461301, "start": "/Date(1511677623263)/"}]}, {"deviceID": 11, "interactions": [{"duration": 1.9378448041499645, "start": "/Date(1511677623263)/"}]}, {"deviceID": 12, "interactions": [{"duration": 2.5737930605218216, "start": "/Date(1511677623263)/"}]}, {"deviceID": 13, "interactions": [{"duration": 2.4336644302997477, "start": "/Date(1511677623263)/"}]}, {"deviceID": 14, "interactions": [{"duration": 4.762140181577479, "start": "/Date(1511677623263)/"}]}, {"deviceID": 15, "interactions": [{"duration": 1.7640011258099628, "start": "/Date(1511677623263)/"}]}, {"deviceID": 16, "interactions": [{"duration": 3.329494782361215, "start": "/Date(1511677623263)/"}]}, {"deviceID": 17, "interactions": [{"duration": 2.428926207245721, "start": "/Date(1511677623263)/"}]}, {"deviceID": 18, "interactions": [{"duration": 3.0367778418056663, "start": "/Date(1511677623263)/"}]}, {"deviceID": 19, "interactions": [{"duration": 7.206956781047751, "start": "/Date(1511677623263)/"}]}, {"deviceID": 20, "interactions": [{"duration": 2.0603564463235586, "start": "/Date(1511677623263)/"}]}, {"deviceID": 21, "interactions": [{"duration": 4.00054227322216, "start": "/Date(1511677623263)/"}]}, {"deviceID": 22, "interactions": [{"duration": 4.793156114941796, "start": "/Date(1511677623263)/"}]}, {"deviceID": 23, "interactions": [{"duration": 5.549100398317085, "start": "/Date(1511677623263)/"}]}, {"deviceID": 24, "interactions": [{"duration": 0.53544543996657, "start": "/Date(1511677623263)/"}]}, {"deviceID": 25, "interactions": [{"duration": 3.339845565067975, "start": "/Date(1511677623263)/"}]}, {"deviceID": 26, "interactions": [{"duration": 1.949377384477931, "start": "/Date(1511677623263)/"}]}, {"deviceID": 27, "interactions": [{"duration": 3.4430695372794635, "start": "/Date(1511677623263)/"}]}, {"deviceID": 28, "interactions": [{"duration": 2.4609493113152636, "start": "/Date(1511677623263)/"}]}, {"deviceID": 29, "interactions": [{"duration": 3.2017335325827467, "start": "/Date(1511677623263)/"}]}, {"deviceID": 30, "interactions": [{"duration": 4.000128568833739, "start": "/Date(1511677623263)/"}]}, {"deviceID": 31, "interactions": [{"duration": 1.8594446232962543, "start": "/Date(1511677623263)/"}]}, {"deviceID": 0, "interactions": [{"duration": 2.733749482606175, "start": "/Date(1511677623899)/"}]}, {"deviceID": 2, "interactions": [{"duration": 4.948677610309265, "start": "/Date(1511677623899)/"}]}, {"deviceID": 3, "interactions": [{"duration": 3.973936678003938, "start": "/Date(1511677623899)/"}]}, {"deviceID": 4, "interactions": [{"duration": 4.341054116204405, "start": "/Date(1511677623899)/"}]}, {"deviceID": 5, "interactions": [{"duration": 6.4100527681607815, "start": "/Date(1511677623899)/"}]}, {"deviceID": 6, "interactions": [{"duration": 4.440595446351493, "start": "/Date(1511677623899)/"}]}, {"deviceID": 7, "interactions": [{"duration": 4.813661344539435, "start": "/Date(1511677623899)/"}]}, {"deviceID": 9, "interactions": [{"duration": 2.8473992631932687, "start": "/Date(1511677623899)/"}]}, {"deviceID": 10, "interactions": [{"duration": 5.457193581859518, "start": "/Date(1511677623899)/"}]}, {"deviceID": 11, "interactions": [{"duration": 2.312075257787808, "start": "/Date(1511677623899)/"}]}, {"deviceID": 12, "interactions": [{"duration": 2.885123283679901, "start": "/Date(1511677623899)/"}]}, {"deviceID": 13, "interactions": [{"duration": 2.8706258624263414, "start": "/Date(1511677623899)/"}]}, {"deviceID": 14, "interactions": [{"duration": 5.921076758617582, "start": "/Date(1511677623899)/"}]}, {"deviceID": 15, "interactions": [{"duration": 2.0863972713455454, "start": "/Date(1511677623899)/"}]}, {"deviceID": 16, "interactions": [{"duration": 2.8098257826915805, "start": "/Date(1511677623899)/"}]}, {"deviceID": 17, "interactions": [{"duration": 3.369383936419211, "start": "/Date(1511677623899)/"}]}, {"deviceID": 18, "interactions": [{"duration": 2.9776579262335576, "start": "/Date(1511677623899)/"}]}, {"deviceID": 20, "interactions": [{"duration": 1.1891534776326282, "start": "/Date(1511677623899)/"}]}, {"deviceID": 21, "interactions": [{"duration": 3.097393738959003, "start": "/Date(1511677623899)/"}]}, {"deviceID": 23, "interactions": [{"duration": 4.629686787058727, "start": "/Date(1511677623899)/"}]}, {"deviceID": 24, "interactions": [{"duration": 1.524404727777776, "start": "/Date(1511677623899)/"}]}, {"deviceID": 25, "interactions": [{"duration": 3.686625139376222, "start": "/Date(1511677623899)/"}]}, {"deviceID": 26, "interactions": [{"duration": 2.433202610184621, "start": "/Date(1511677623899)/"}]}, {"deviceID": 27, "interactions": [{"duration": 3.26015660714512, "start": "/Date(1511677623899)/"}]}, {"deviceID": 28, "interactions": [{"duration": 3.475661393754914, "start": "/Date(1511677623899)/"}]}, {"deviceID": 29, "interactions": [{"duration": 3.327146925764953, "start": "/Date(1511677623899)/"}]}, {"deviceID": 30, "interactions": [{"duration": 4.676980912898683, "start": "/Date(1511677623899)/"}]}, {"deviceID": 31, "interactions": [{"duration": 1.789546014415577, "start": "/Date(1511677623899)/"}]}, {"deviceID": 0, "interactions": [{"duration": 1.4236727264634053, "start": "/Date(1511677624501)/"}]}, {"deviceID": 1, "interactions": [{"duration": 7.53054785591225, "start": "/Date(1511677624501)/"}]}, {"deviceID": 3, "interactions": [{"duration": 4.641182711383548, "start": "/Date(1511677624501)/"}]}, {"deviceID": 4, "interactions": [{"duration": 3.7978650487501238, "start": "/Date(1511677624501)/"}]}, {"deviceID": 5, "interactions": [{"duration": 6.41539377563415, "start": "/Date(1511677624501)/"}]}, {"deviceID": 6, "interactions": [{"duration": 5.592753000880759, "start": "/Date(1511677624501)/"}]}, {"deviceID": 7, "interactions": [{"duration": 4.600034024895937, "start": "/Date(1511677624501)/"}]}, {"deviceID": 9, "interactions": [{"duration": 2.6095694478336906, "start": "/Date(1511677624501)/"}]}, {"deviceID": 10, "interactions": [{"duration": 5.10706478576561, "start": "/Date(1511677624501)/"}]}, {"deviceID": 11, "interactions": [{"duration": 3.1125577956871764, "start": "/Date(1511677624501)/"}]}, {"deviceID": 12, "interactions": [{"duration": 3.2303924046568038, "start": "/Date(1511677624501)/"}]}, {"deviceID": 13, "interactions": [{"duration": 2.4276401834056305, "start": "/Date(1511677624501)/"}]}, {"deviceID": 14, "interactions": [{"duration": 3.9761354042837924, "start": "/Date(1511677624501)/"}]}, {"deviceID": 15, "interactions": [{"duration": 2.116356574940295, "start": "/Date(1511677624501)/"}]}, {"deviceID": 17, "interactions": [{"duration": 3.3437897890670167, "start": "/Date(1511677624501)/"}]}, {"deviceID": 18, "interactions": [{"duration": 2.9645415920571487, "start": "/Date(1511677624501)/"}]}, {"deviceID": 19, "interactions": [{"duration": 5.476098811158986, "start": "/Date(1511677624501)/"}]}, {"deviceID": 21, "interactions": [{"duration": 3.1219459165854753, "start": "/Date(1511677624501)/"}]}, {"deviceID": 22, "interactions": [{"duration": 4.525926684711549, "start": "/Date(1511677624501)/"}]}, {"deviceID": 23, "interactions": [{"duration": 5.118494197157216, "start": "/Date(1511677624501)/"}]}, {"deviceID": 24, "interactions": [{"duration": 0.811009692990029, "start": "/Date(1511677624501)/"}]}, {"deviceID": 25, "interactions": [{"duration": 3.361248845577367, "start": "/Date(1511677624501)/"}]}, {"deviceID": 26, "interactions": [{"duration": 2.7783158831774393, "start": "/Date(1511677624501)/"}]}, {"deviceID": 27, "interactions": [{"duration": 2.158922300652341, "start": "/Date(1511677624501)/"}]}, {"deviceID": 28, "interactions": [{"duration": 2.693910284648214, "start": "/Date(1511677624501)/"}]}, {"deviceID": 29, "interactions": [{"duration": 3.342821655807917, "start": "/Date(1511677624501)/"}]}, {"deviceID": 30, "interactions": [{"duration": 4.157951391836196, "start": "/Date(1511677624501)/"}]}, {"deviceID": 31, "interactions": [{"duration": 2.4561189679998314, "start": "/Date(1511677624501)/"}]}, {"deviceID": 1, "interactions": [{"duration": 6.707485900403059, "start": "/Date(1511677625147)/"}]}, {"deviceID": 2, "interactions": [{"duration": 4.29055069848253, "start": "/Date(1511677625147)/"}]}, {"deviceID": 3, "interactions": [{"duration": 4.407245363797277, "start": "/Date(1511677625147)/"}]}, {"deviceID": 4, "interactions": [{"duration": 5.056042654183697, "start": "/Date(1511677625147)/"}]}, {"deviceID": 5, "interactions": [{"duration": 6.195809222785037, "start": "/Date(1511677625147)/"}]}, {"deviceID": 6, "interactions": [{"duration": 4.6052348258940965, "start": "/Date(1511677625147)/"}]}, {"deviceID": 8, "interactions": [{"duration": 2.547148209013785, "start": "/Date(1511677625147)/"}]}, {"deviceID": 9, "interactions": [{"duration": 3.8449877467121483, "start": "/Date(1511677625147)/"}]}, {"deviceID": 10, "interactions": [{"duration": 5.214334509818924, "start": "/Date(1511677625147)/"}]}, {"deviceID": 11, "interactions": [{"duration": 2.4359937678292356, "start": "/Date(1511677625147)/"}]}, {"deviceID": 12, "interactions": [{"duration": 2.8468386722844166, "start": "/Date(1511677625147)/"}]}, {"deviceID": 13, "interactions": [{"duration": 2.777485837971429, "start": "/Date(1511677625147)/"}]}, {"deviceID": 15, "interactions": [{"duration": 1.8979371132103537, "start": "/Date(1511677625147)/"}]}, {"deviceID": 16, "interactions": [{"duration": 2.55025460284787, "start": "/Date(1511677625147)/"}]}, {"deviceID": 17, "interactions": [{"duration": 2.9776555197945918, "start": "/Date(1511677625147)/"}]}, {"deviceID": 19, "interactions": [{"duration": 5.497385272855595, "start": "/Date(1511677625147)/"}]}, {"deviceID": 20, "interactions": [{"duration": 1.7595106870724067, "start": "/Date(1511677625147)/"}]}, {"deviceID": 21, "interactions": [{"duration": 3.8033647124674386, "start": "/Date(1511677625147)/"}]}, {"deviceID": 22, "interactions": [{"duration": 4.555655547746571, "start": "/Date(1511677625147)/"}]}, {"deviceID": 23, "interactions": [{"duration": 4.8568539263610075, "start": "/Date(1511677625147)/"}]}, {"deviceID": 24, "interactions": [{"duration": 1.2034514005067267, "start": "/Date(1511677625147)/"}]}, {"deviceID": 27, "interactions": [{"duration": 2.438595250391484, "start": "/Date(1511677625147)/"}]}, {"deviceID": 28, "interactions": [{"duration": 3.3364736774987183, "start": "/Date(1511677625147)/"}]}, {"deviceID": 0, "interactions": [{"duration": 1.9932816275051601, "start": "/Date(1511677625747)/"}]}, {"deviceID": 2, "interactions": [{"duration": 3.6663321771977193, "start": "/Date(1511677625747)/"}]}, {"deviceID": 4, "interactions": [{"duration": 4.760305207625226, "start": "/Date(1511677625747)/"}]}, {"deviceID": 5, "interactions": [{"duration": 6.412941696992713, "start": "/Date(1511677625747)/"}]}, {"deviceID": 6, "interactions": [{"duration": 5.096501617182812, "start": "/Date(1511677625747)/"}]}, {"deviceID": 7, "interactions": [{"duration": 5.201710989833985, "start": "/Date(1511677625747)/"}]}, {"deviceID": 8, "interactions": [{"duration": 2.9341515912257483, "start": "/Date(1511677625747)/"}]}, {"deviceID": 9, "interactions": [{"duration": 3.5473513641186845, "start": "/Date(1511677625747)/"}]}, {"deviceID": 11, "interactions": [{"duration": 2.75896510694387, "start": "/Date(1511677625747)/"}]}, {"deviceID": 12, "interactions": [{"duration": 2.7503410613573114, "start": "/Date(1511677625747)/"}]}, {"deviceID": 13, "interactions": [{"duration": 2.565757096668676, "start": "/Date(1511677625747)/"}]}, {"deviceID": 14, "interactions": [{"duration": 4.763397126021513, "start": "/Date(1511677625747)/"}]}, {"deviceID": 15, "interactions": [{"duration": 2.3820391817413515, "start": "/Date(1511677625747)/"}]}, {"deviceID": 16, "interactions": [{"duration": 2.307110558422625, "start": "/Date(1511677625747)/"}]}, {"deviceID": 17, "interactions": [{"duration": 2.84367707066903, "start": "/Date(1511677625747)/"}]}, {"deviceID": 18, "interactions": [{"duration": 3.4018882268136457, "start": "/Date(1511677625747)/"}]}, {"deviceID": 19, "interactions": [{"duration": 6.117722396553279, "start": "/Date(1511677625747)/"}]}, {"deviceID": 21, "interactions": [{"duration": 4.92699132985834, "start": "/Date(1511677625747)/"}]}, {"deviceID": 22, "interactions": [{"duration": 4.93542266929954, "start": "/Date(1511677625747)/"}]}, {"deviceID": 24, "interactions": [{"duration": 0.9022728103805837, "start": "/Date(1511677625747)/"}]}, {"deviceID": 26, "interactions": [{"duration": 1.8630330764198144, "start": "/Date(1511677625747)/"}]}, {"deviceID": 27, "interactions": [{"duration": 3.045966797151361, "start": "/Date(1511677625747)/"}]}, {"deviceID": 28, "interactions": [{"duration": 3.0110069937579254, "start": "/Date(1511677625747)/"}]}, {"deviceID": 29, "interactions": [{"duration": 2.4628189806887857, "start": "/Date(1511677625747)/"}]}, {"deviceID": 30, "interactions": [{"duration": 4.006152086700048, "start": "/Date(1511677625747)/"}]}, {"deviceID": 31, "interactions": [{"duration": 1.4010814544577097, "start": "/Date(1511677625747)/"}]}, {"deviceID": 0, "interactions": [{"duration": 2.763040270363106, "start": "/Date(1511677626322)/"}]}, {"deviceID": 1, "interactions": [{"duration": 7.278516467403418, "start": "/Date(1511677626322)/"}]}, {"deviceID": 2, "interactions": [{"duration": 4.48290016509951, "start": "/Date(1511677626322)/"}]}, {"deviceID": 3, "interactions": [{"duration": 3.98526731254344, "start": "/Date(1511677626322)/"}]}, {"deviceID": 4, "interactions": [{"duration": 3.8959283580476143, "start": "/Date(1511677626322)/"}]}, {"deviceID": 5, "interactions": [{"duration": 6.007484535511165, "start": "/Date(1511677626322)/"}]}, {"deviceID": 6, "interactions": [{"duration": 4.472791524976937, "start": "/Date(1511677626322)/"}]}, {"deviceID": 8, "interactions": [{"duration": 2.459090327396334, "start": "/Date(1511677626322)/"}]}, {"deviceID": 9, "interactions": [{"duration": 2.929749412861114, "start": "/Date(1511677626322)/"}]}, {"deviceID": 10, "interactions": [{"duration": 5.188556307795776, "start": "/Date(1511677626322)/"}]}, {"deviceID": 12, "interactions": [{"duration": 2.5184198603351784, "start": "/Date(1511677626322)/"}]}, {"deviceID": 13, "interactions": [{"duration": 3.7922720981663955, "start": "/Date(1511677626322)/"}]}, {"deviceID": 14, "interactions": [{"duration": 5.071750867756905, "start": "/Date(1511677626322)/"}]}, {"deviceID": 15, "interactions": [{"duration": 1.7696794518777568, "start": "/Date(1511677626322)/"}]}, {"deviceID": 17, "interactions": [{"duration": 2.7515553082945012, "start": "/Date(1511677626322)/"}]}, {"deviceID": 18, "interactions": [{"duration": 3.129940214913458, "start": "/Date(1511677626322)/"}]}, {"deviceID": 19, "interactions": [{"duration": 5.45238161853836, "start": "/Date(1511677626322)/"}]}, {"deviceID": 20, "interactions": [{"duration": 2.1186577201442494, "start": "/Date(1511677626322)/"}]}, {"deviceID": 21, "interactions": [{"duration": 3.17913417176391, "start": "/Date(1511677626322)/"}]}, {"deviceID": 23, "interactions": [{"duration": 4.717463490165529, "start": "/Date(1511677626322)/"}]}, {"deviceID": 25, "interactions": [{"duration": 3.505094132059712, "start": "/Date(1511677626322)/"}]}, {"deviceID": 26, "interactions": [{"duration": 1.5754138398745594, "start": "/Date(1511677626322)/"}]}, {"deviceID": 27, "interactions": [{"duration": 3.1901906659597983, "start": "/Date(1511677626322)/"}]}, {"deviceID": 28, "interactions": [{"duration": 3.420105480577819, "start": "/Date(1511677626322)/"}]}, {"deviceID": 30, "interactions": [{"duration": 3.952992936700021, "start": "/Date(1511677626322)/"}]}, {"deviceID": 0, "interactions": [{"duration": 1.470567742587623, "start": "/Date(1511677626848)/"}]}, {"deviceID": 2, "interactions": [{"duration": 3.7193476485295505, "start": "/Date(1511677626848)/"}]}, {"deviceID": 3, "interactions": [{"duration": 4.512593686858042, "start": "/Date(1511677626848)/"}]}, {"deviceID": 5, "interactions": [{"duration": 5.675432407790906, "start": "/Date(1511677626848)/"}]}, {"deviceID": 6, "interactions": [{"duration": 5.496018559159587, "start": "/Date(1511677626848)/"}]}, {"deviceID": 8, "interactions": [{"duration": 2.4885397236731825, "start": "/Date(1511677626848)/"}]}, {"deviceID": 10, "interactions": [{"duration": 5.051205333901317, "start": "/Date(1511677626848)/"}]}, {"deviceID": 11, "interactions": [{"duration": 2.108853692866782, "start": "/Date(1511677626848)/"}]}, {"deviceID": 12, "interactions": [{"duration": 3.282376515230346, "start": "/Date(1511677626848)/"}]}, {"deviceID": 13, "interactions": [{"duration": 2.543932513376186, "start": "/Date(1511677626848)/"}]}, {"deviceID": 14, "interactions": [{"duration": 4.9318854416071005, "start": "/Date(1511677626848)/"}]}, {"deviceID": 15, "interactions": [{"duration": 1.4920831644372528, "start": "/Date(1511677626848)/"}]}, {"deviceID": 16, "interactions": [{"duration": 2.960659208457757, "start": "/Date(1511677626848)/"}]}, {"deviceID": 19, "interactions": [{"duration": 6.05721880653767, "start": "/Date(1511677626848)/"}]}, {"deviceID": 20, "interactions": [{"duration": 1.7008145242814754, "start": "/Date(1511677626848)/"}]}, {"deviceID": 21, "interactions": [{"duration": 3.543133848360218, "start": "/Date(1511677626848)/"}]}, {"deviceID": 22, "interactions": [{"duration": 4.9041155802709495, "start": "/Date(1511677626848)/"}]}, {"deviceID": 24, "interactions": [{"duration": 1.1112742129687243, "start": "/Date(1511677626848)/"}]}, {"deviceID": 25, "interactions": [{"duration": 3.46412383502438, "start": "/Date(1511677626848)/"}]}, {"deviceID": 26, "interactions": [{"duration": 2.092493994500707, "start": "/Date(1511677626848)/"}]}, {"deviceID": 27, "interactions": [{"duration": 3.2628192821783193, "start": "/Date(1511677626848)/"}]}, {"deviceID": 28, "interactions": [{"duration": 2.662287658856331, "start": "/Date(1511677626848)/"}]}, {"deviceID": 30, "interactions": [{"duration": 4.177044431040777, "start": "/Date(1511677626848)/"}]}, {"deviceID": 31, "interactions": [{"duration": 2.059179886562376, "start": "/Date(1511677626848)/"}]}, {"deviceID": 0, "interactions": [{"duration": 2.4219382864670265, "start": "/Date(1511677627431)/"}]}, {"deviceID": 1, "interactions": [{"duration": 7.441491030445766, "start": "/Date(1511677627431)/"}]}, {"deviceID": 2, "interactions": [{"duration": 3.656981987279088, "start": "/Date(1511677627431)/"}]}, {"deviceID": 4, "interactions": [{"duration": 3.858759492746794, "start": "/Date(1511677627431)/"}]}, {"deviceID": 5, "interactions": [{"duration": 6.94849434303533, "start": "/Date(1511677627431)/"}]}, {"deviceID": 6, "interactions": [{"duration": 4.841895938180638, "start": "/Date(1511677627431)/"}]}, {"deviceID": 7, "interactions": [{"duration": 6.156807643341708, "start": "/Date(1511677627431)/"}]}, {"deviceID": 8, "interactions": [{"duration": 3.679437306986185, "start": "/Date(1511677627431)/"}]}, {"deviceID": 9, "interactions": [{"duration": 3.006589610398142, "start": "/Date(1511677627431)/"}]}, {"deviceID": 10, "interactions": [{"duration": 5.506911723373622, "start": "/Date(1511677627431)/"}]}, {"deviceID": 11, "interactions": [{"duration": 1.0975986659601025, "start": "/Date(1511677627431)/"}]}, {"deviceID": 12, "interactions": [{"duration": 3.384665516796189, "start": "/Date(1511677627431)/"}]}, {"deviceID": 13, "interactions": [{"duration": 3.9003234680620946, "start": "/Date(1511677627431)/"}]}, {"deviceID": 14, "interactions": [{"duration": 3.692516582627624, "start": "/Date(1511677627431)/"}]}, {"deviceID": 15, "interactions": [{"duration": 0.6699138476123774, "start": "/Date(1511677627431)/"}]}, {"deviceID": 16, "interactions": [{"duration": 2.9592427532172016, "start": "/Date(1511677627431)/"}]}, {"deviceID": 17, "interactions": [{"duration": 2.430384565980379, "start": "/Date(1511677627431)/"}]}, {"deviceID": 18, "interactions": [{"duration": 3.444377060168156, "start": "/Date(1511677627431)/"}]}, {"deviceID": 19, "interactions": [{"duration": 6.295997433945915, "start": "/Date(1511677627431)/"}]}, {"deviceID": 20, "interactions": [{"duration": 1.7010417866478176, "start": "/Date(1511677627431)/"}]}, {"deviceID": 21, "interactions": [{"duration": 4.148103260376473, "start": "/Date(1511677627431)/"}]}, {"deviceID": 22, "interactions": [{"duration": 3.871783406614394, "start": "/Date(1511677627431)/"}]}, {"deviceID": 23, "interactions": [{"duration": 5.4791903686479015, "start": "/Date(1511677627431)/"}]}, {"deviceID": 24, "interactions": [{"duration": 1.101853549961309, "start": "/Date(1511677627431)/"}]}, {"deviceID": 25, "interactions": [{"duration": 2.652025670209893, "start": "/Date(1511677627431)/"}]}, {"deviceID": 26, "interactions": [{"duration": 1.6649222135018897, "start": "/Date(1511677627431)/"}]}, {"deviceID": 27, "interactions": [{"duration": 2.928408553996032, "start": "/Date(1511677627431)/"}]}, {"deviceID": 29, "interactions": [{"duration": 2.794276359126786, "start": "/Date(1511677627431)/"}]}, {"deviceID": 30, "interactions": [{"duration": 4.087814972274044, "start": "/Date(1511677627431)/"}]}, {"deviceID": 31, "interactions": [{"duration": 1.7848758530370248, "start": "/Date(1511677627431)/"}]}, {"deviceID": 0, "interactions": [{"duration": 2.3535167781931783, "start": "/Date(1511677627993)/"}]}, {"deviceID": 1, "interactions": [{"duration": 6.923878018029719, "start": "/Date(1511677627993)/"}]}, {"deviceID": 2, "interactions": [{"duration": 3.6274747588876552, "start": "/Date(1511677627993)/"}]}, {"deviceID": 3, "interactions": [{"duration": 3.008654586047652, "start": "/Date(1511677627993)/"}]}, {"deviceID": 4, "interactions": [{"duration": 3.935422956067785, "start": "/Date(1511677627993)/"}]}, {"deviceID": 5, "interactions": [{"duration": 6.019157305614712, "start": "/Date(1511677627993)/"}]}, {"deviceID": 7, "interactions": [{"duration": 5.720343412299699, "start": "/Date(1511677627993)/"}]}, {"deviceID": 8, "interactions": [{"duration": 2.825820559565364, "start": "/Date(1511677627993)/"}]}, {"deviceID": 10, "interactions": [{"duration": 4.7197258005626415, "start": "/Date(1511677627993)/"}]}, {"deviceID": 11, "interactions": [{"duration": 2.905611490958078, "start": "/Date(1511677627993)/"}]}, {"deviceID": 12, "interactions": [{"duration": 3.178346224575144, "start": "/Date(1511677627993)/"}]}, {"deviceID": 14, "interactions": [{"duration": 5.345193751504578, "start": "/Date(1511677627993)/"}]}, {"deviceID": 15, "interactions": [{"duration": 2.776408077239794, "start": "/Date(1511677627993)/"}]}, {"deviceID": 16, "interactions": [{"duration": 3.326574448580579, "start": "/Date(1511677627993)/"}]}, {"deviceID": 17, "interactions": [{"duration": 2.70114720765324, "start": "/Date(1511677627993)/"}]}, {"deviceID": 18, "interactions": [{"duration": 3.385587872539789, "start": "/Date(1511677627993)/"}]}, {"deviceID": 20, "interactions": [{"duration": 2.18626301878429, "start": "/Date(1511677627993)/"}]}, {"deviceID": 22, "interactions": [{"duration": 5.0587045938141895, "start": "/Date(1511677627993)/"}]}, {"deviceID": 23, "interactions": [{"duration": 4.417092687188242, "start": "/Date(1511677627993)/"}]}, {"deviceID": 25, "interactions": [{"duration": 4.0426514993162765, "start": "/Date(1511677627993)/"}]}, {"deviceID": 26, "interactions": [{"duration": 2.3938626590738745, "start": "/Date(1511677627993)/"}]}, {"deviceID": 27, "interactions": [{"duration": 3.0426412119027884, "start": "/Date(1511677627993)/"}]}, {"deviceID": 28, "interactions": [{"duration": 3.31092474203448, "start": "/Date(1511677627993)/"}]}, {"deviceID": 29, "interactions": [{"duration": 3.166714035171405, "start": "/Date(1511677627993)/"}]}, {"deviceID": 30, "interactions": [{"duration": 3.923744128121803, "start": "/Date(1511677627993)/"}]}, {"deviceID": 31, "interactions": [{"duration": 1.5702655756995227, "start": "/Date(1511677627993)/"}]}, {"deviceID": 0, "interactions": [{"duration": 1.780431875476987, "start": "/Date(1511677628594)/"}]}, {"deviceID": 2, "interactions": [{"duration": 4.682780641803941, "start": "/Date(1511677628594)/"}]}, {"deviceID": 3, "interactions": [{"duration": 3.0522816315663914, "start": "/Date(1511677628594)/"}]}, {"deviceID": 4, "interactions": [{"duration": 4.581395959893984, "start": "/Date(1511677628594)/"}]}, {"deviceID": 6, "interactions": [{"duration": 4.847696772895938, "start": "/Date(1511677628594)/"}]}, {"deviceID": 7, "interactions": [{"duration": 4.984607108309341, "start": "/Date(1511677628594)/"}]}, {"deviceID": 8, "interactions": [{"duration": 2.154935241282688, "start": "/Date(1511677628594)/"}]}, {"deviceID": 9, "interactions": [{"duration": 2.745776536891025, "start": "/Date(1511677628594)/"}]}, {"deviceID": 10, "interactions": [{"duration": 5.2724324192698475, "start": "/Date(1511677628594)/"}]}, {"deviceID": 11, "interactions": [{"duration": 2.7739246418803742, "start": "/Date(1511677628594)/"}]}, {"deviceID": 13, "interactions": [{"duration": 2.8785515769241505, "start": "/Date(1511677628594)/"}]}, {"deviceID": 14, "interactions": [{"duration": 5.022670674685844, "start": "/Date(1511677628594)/"}]}, {"deviceID": 15, "interactions": [{"duration": 2.2292076971736066, "start": "/Date(1511677628594)/"}]}, {"deviceID": 17, "interactions": [{"duration": 1.943454809624519, "start": "/Date(1511677628594)/"}]}, {"deviceID": 18, "interactions": [{"duration": 2.7629358649314906, "start": "/Date(1511677628594)/"}]}, {"deviceID": 19, "interactions": [{"duration": 5.995460868775487, "start": "/Date(1511677628594)/"}]}, {"deviceID": 21, "interactions": [{"duration": 3.9585363920211036, "start": "/Date(1511677628594)/"}]}, {"deviceID": 22, "interactions": [{"duration": 5.220961092149875, "start": "/Date(1511677628594)/"}]}, {"deviceID": 23, "interactions": [{"duration": 5.069318293180478, "start": "/Date(1511677628594)/"}]}, {"deviceID": 24, "interactions": [{"duration": 1.134778642698379, "start": "/Date(1511677628594)/"}]}, {"deviceID": 25, "interactions": [{"duration": 3.302011139839228, "start": "/Date(1511677628594)/"}]}, {"deviceID": 26, "interactions": [{"duration": 2.424339431914095, "start": "/Date(1511677628594)/"}]}, {"deviceID": 27, "interactions": [{"duration": 2.6244244992799612, "start": "/Date(1511677628594)/"}]}, {"deviceID": 28, "interactions": [{"duration": 3.1906655370365913, "start": "/Date(1511677628594)/"}]}, {"deviceID": 29, "interactions": [{"duration": 3.0604420129752365, "start": "/Date(1511677628594)/"}]}, {"deviceID": 30, "interactions": [{"duration": 3.292857016287463, "start": "/Date(1511677628594)/"}]}, {"deviceID": 31, "interactions": [{"duration": 2.152462743106433, "start": "/Date(1511677628594)/"}]}, {"deviceID": 0, "interactions": [{"duration": 1.3811557744093321, "start": "/Date(1511677629171)/"}]}, {"deviceID": 2, "interactions": [{"duration": 4.414668371157961, "start": "/Date(1511677629171)/"}]}, {"deviceID": 4, "interactions": [{"duration": 3.3436258893751756, "start": "/Date(1511677629171)/"}]}, {"deviceID": 6, "interactions": [{"duration": 5.453525161619766, "start": "/Date(1511677629171)/"}]}, {"deviceID": 7, "interactions": [{"duration": 4.85392348132731, "start": "/Date(1511677629171)/"}]}, {"deviceID": 8, "interactions": [{"duration": 3.2697871189362107, "start": "/Date(1511677629171)/"}]}, {"deviceID": 9, "interactions": [{"duration": 2.390391026083695, "start": "/Date(1511677629171)/"}]}, {"deviceID": 10, "interactions": [{"duration": 4.540315702214236, "start": "/Date(1511677629171)/"}]}, {"deviceID": 11, "interactions": [{"duration": 2.0708202455020044, "start": "/Date(1511677629171)/"}]}, {"deviceID": 12, "interactions": [{"duration": 3.8566887182292757, "start": "/Date(1511677629171)/"}]}, {"deviceID": 13, "interactions": [{"duration": 2.9659027566779446, "start": "/Date(1511677629171)/"}]}, {"deviceID": 14, "interactions": [{"duration": 5.407174529043023, "start": "/Date(1511677629171)/"}]}, {"deviceID": 15, "interactions": [{"duration": 2.1973233611711134, "start": "/Date(1511677629171)/"}]}, {"deviceID": 16, "interactions": [{"duration": 3.0916120071336484, "start": "/Date(1511677629171)/"}]}, {"deviceID": 17, "interactions": [{"duration": 3.1661114891996673, "start": "/Date(1511677629171)/"}]}, {"deviceID": 18, "interactions": [{"duration": 3.4066217652960216, "start": "/Date(1511677629171)/"}]}, {"deviceID": 21, "interactions": [{"duration": 2.925038268743781, "start": "/Date(1511677629171)/"}]}, {"deviceID": 23, "interactions": [{"duration": 4.672592522756474, "start": "/Date(1511677629171)/"}]}, {"deviceID": 24, "interactions": [{"duration": 1.6174676422543253, "start": "/Date(1511677629171)/"}]}, {"deviceID": 25, "interactions": [{"duration": 3.9656161835758224, "start": "/Date(1511677629171)/"}]}, {"deviceID": 26, "interactions": [{"duration": 2.615069135212345, "start": "/Date(1511677629171)/"}]}, {"deviceID": 29, "interactions": [{"duration": 2.8246788885564516, "start": "/Date(1511677629171)/"}]}, {"deviceID": 30, "interactions": [{"duration": 4.32613104013791, "start": "/Date(1511677629171)/"}]}, {"deviceID": 31, "interactions": [{"duration": 1.7235774740148808, "start": "/Date(1511677629171)/"}]}, {"deviceID": 0, "interactions": [{"duration": 1.6938764168419764, "start": "/Date(1511677629746)/"}]}, {"deviceID": 1, "interactions": [{"duration": 7.8977726571525295, "start": "/Date(1511677629746)/"}]}, {"deviceID": 3, "interactions": [{"duration": 3.733497945237787, "start": "/Date(1511677629746)/"}]}, {"deviceID": 4, "interactions": [{"duration": 3.5918453069670653, "start": "/Date(1511677629746)/"}]}, {"deviceID": 8, "interactions": [{"duration": 3.125472022960059, "start": "/Date(1511677629746)/"}]}, {"deviceID": 9, "interactions": [{"duration": 3.178914718771424, "start": "/Date(1511677629746)/"}]}, {"deviceID": 10, "interactions": [{"duration": 5.7751349600487325, "start": "/Date(1511677629746)/"}]}, {"deviceID": 11, "interactions": [{"duration": 2.3213930932859275, "start": "/Date(1511677629746)/"}]}, {"deviceID": 12, "interactions": [{"duration": 2.9935741375211147, "start": "/Date(1511677629746)/"}]}, {"deviceID": 14, "interactions": [{"duration": 5.034449464016897, "start": "/Date(1511677629746)/"}]}, {"deviceID": 15, "interactions": [{"duration": 2.3955432269704158, "start": "/Date(1511677629746)/"}]}, {"deviceID": 16, "interactions": [{"duration": 2.461535392998082, "start": "/Date(1511677629746)/"}]}, {"deviceID": 18, "interactions": [{"duration": 2.8984518794536287, "start": "/Date(1511677629746)/"}]}, {"deviceID": 20, "interactions": [{"duration": 2.3835265285720637, "start": "/Date(1511677629746)/"}]}, {"deviceID": 23, "interactions": [{"duration": 5.00753025734938, "start": "/Date(1511677629746)/"}]}, {"deviceID": 24, "interactions": [{"duration": 1.3738635481707628, "start": "/Date(1511677629746)/"}]}, {"deviceID": 25, "interactions": [{"duration": 2.567490636348146, "start": "/Date(1511677629746)/"}]}, {"deviceID": 26, "interactions": [{"duration": 2.110708368450529, "start": "/Date(1511677629746)/"}]}, {"deviceID": 28, "interactions": [{"duration": 2.824216710893835, "start": "/Date(1511677629746)/"}]}, {"deviceID": 29, "interactions": [{"duration": 3.52385799284749, "start": "/Date(1511677629746)/"}]}, {"deviceID": 30, "interactions": [{"duration": 3.14513404063164, "start": "/Date(1511677629746)/"}]}, {"deviceID": 31, "interactions": [{"duration": 1.8830479728257488, "start": "/Date(1511677629746)/"}]}, {"deviceID": 0, "interactions": [{"duration": 1.426996086196878, "start": "/Date(1511677630398)/"}]}, {"deviceID": 1, "interactions": [{"duration": 6.690434318991739, "start": "/Date(1511677630398)/"}]}, {"deviceID": 2, "interactions": [{"duration": 4.363848690676832, "start": "/Date(1511677630398)/"}]}, {"deviceID": 3, "interactions": [{"duration": 3.4941556891191836, "start": "/Date(1511677630398)/"}]}, {"deviceID": 4, "interactions": [{"duration": 3.3972465490439703, "start": "/Date(1511677630398)/"}]}, {"deviceID": 6, "interactions": [{"duration": 4.830570652410799, "start": "/Date(1511677630398)/"}]}, {"deviceID": 8, "interactions": [{"duration": 2.8909943341522855, "start": "/Date(1511677630398)/"}]}, {"deviceID": 9, "interactions": [{"duration": 2.9992716647459803, "start": "/Date(1511677630398)/"}]}, {"deviceID": 10, "interactions": [{"duration": 5.529633008237266, "start": "/Date(1511677630398)/"}]}, {"deviceID": 11, "interactions": [{"duration": 1.4640387055604993, "start": "/Date(1511677630398)/"}]}, {"deviceID": 12, "interactions": [{"duration": 2.725624308121747, "start": "/Date(1511677630398)/"}]}, {"deviceID": 13, "interactions": [{"duration": 2.8806835049237396, "start": "/Date(1511677630398)/"}]}, {"deviceID": 14, "interactions": [{"duration": 4.906278488544379, "start": "/Date(1511677630398)/"}]}, {"deviceID": 15, "interactions": [{"duration": 2.52624978654878, "start": "/Date(1511677630398)/"}]}, {"deviceID": 16, "interactions": [{"duration": 2.2954928002009383, "start": "/Date(1511677630398)/"}]}, {"deviceID": 17, "interactions": [{"duration": 2.9275119003841885, "start": "/Date(1511677630398)/"}]}, {"deviceID": 19, "interactions": [{"duration": 6.596761782556312, "start": "/Date(1511677630398)/"}]}, {"deviceID": 21, "interactions": [{"duration": 4.351754733173627, "start": "/Date(1511677630398)/"}]}, {"deviceID": 22, "interactions": [{"duration": 4.313533950853132, "start": "/Date(1511677630398)/"}]}, {"deviceID": 23, "interactions": [{"duration": 4.596158694589675, "start": "/Date(1511677630398)/"}]}, {"deviceID": 24, "interactions": [{"duration": 1.8567410077158732, "start": "/Date(1511677630398)/"}]}, {"deviceID": 25, "interactions": [{"duration": 3.125876046252894, "start": "/Date(1511677630398)/"}]}, {"deviceID": 26, "interactions": [{"duration": 2.0913798720541186, "start": "/Date(1511677630398)/"}]}, {"deviceID": 28, "interactions": [{"duration": 1.9510218426573263, "start": "/Date(1511677630398)/"}]}, {"deviceID": 29, "interactions": [{"duration": 2.820039285122016, "start": "/Date(1511677630398)/"}]}, {"deviceID": 30, "interactions": [{"duration": 2.9111496517460185, "start": "/Date(1511677630398)/"}]}, {"deviceID": 31, "interactions": [{"duration": 2.083897878628249, "start": "/Date(1511677630398)/"}]}, {"deviceID": 0, "interactions": [{"duration": 2.514108718189678, "start": "/Date(1511677631036)/"}]}, {"deviceID": 1, "interactions": [{"duration": 6.271039878940318, "start": "/Date(1511677631036)/"}]}, {"deviceID": 2, "interactions": [{"duration": 3.9481114272543034, "start": "/Date(1511677631036)/"}]}, {"deviceID": 3, "interactions": [{"duration": 4.237382428038099, "start": "/Date(1511677631036)/"}]}, {"deviceID": 4, "interactions": [{"duration": 3.6569659002527617, "start": "/Date(1511677631036)/"}]}, {"deviceID": 5, "interactions": [{"duration": 6.442094075148207, "start": "/Date(1511677631036)/"}]}, {"deviceID": 6, "interactions": [{"duration": 5.043786534655423, "start": "/Date(1511677631036)/"}]}, {"deviceID": 7, "interactions": [{"duration": 4.223583123538608, "start": "/Date(1511677631036)/"}]}, {"deviceID": 8, "interactions": [{"duration": 2.242939835819171, "start": "/Date(1511677631036)/"}]}, {"deviceID": 10, "interactions": [{"duration": 4.580775917435183, "start": "/Date(1511677631036)/"}]}, {"deviceID": 11, "interactions": [{"duration": 1.970661661013706, "start": "/Date(1511677631036)/"}]}, {"deviceID": 12, "interactions": [{"duration": 3.024512742771608, "start": "/Date(1511677631036)/"}]}, {"deviceID": 13, "interactions": [{"duration": 2.9605479600764384, "start": "/Date(1511677631036)/"}]}, {"deviceID": 16, "interactions": [{"duration": 2.918474075258401, "start": "/Date(1511677631036)/"}]}, {"deviceID": 17, "interactions": [{"duration": 3.1806637416918666, "start": "/Date(1511677631036)/"}]}, {"deviceID": 18, "interactions": [{"duration": 3.232358644206022, "start": "/Date(1511677631036)/"}]}, {"deviceID": 19, "interactions": [{"duration": 5.933012378937937, "start": "/Date(1511677631036)/"}]}, {"deviceID": 20, "interactions": [{"duration": 1.8089713503538714, "start": "/Date(1511677631036)/"}]}, {"deviceID": 21, "interactions": [{"duration": 4.8680384119332185, "start": "/Date(1511677631036)/"}]}, {"deviceID": 22, "interactions": [{"duration": 5.81252075496659, "start": "/Date(1511677631036)/"}]}, {"deviceID": 23, "interactions": [{"duration": 5.238660125526804, "start": "/Date(1511677631036)/"}]}, {"deviceID": 24, "interactions": [{"duration": 0.4135809738514421, "start": "/Date(1511677631036)/"}]}, {"deviceID": 25, "interactions": [{"duration": 2.886481070835064, "start": "/Date(1511677631036)/"}]}, {"deviceID": 26, "interactions": [{"duration": 1.5473631760095765, "start": "/Date(1511677631036)/"}]}, {"deviceID": 27, "interactions": [{"duration": 3.663496963614591, "start": "/Date(1511677631036)/"}]}, {"deviceID": 28, "interactions": [{"duration": 3.2724495344343922, "start": "/Date(1511677631036)/"}]}, {"deviceID": 29, "interactions": [{"duration": 2.64101327626223, "start": "/Date(1511677631036)/"}]}, {"deviceID": 30, "interactions": [{"duration": 3.2640915116797533, "start": "/Date(1511677631036)/"}]}, {"deviceID": 31, "interactions": [{"duration": 1.1658893340182528, "start": "/Date(1511677631036)/"}]}, {"deviceID": 0, "interactions": [{"duration": 2.0582603846466045, "start": "/Date(1511677631621)/"}]}, {"deviceID": 1, "interactions": [{"duration": 7.381540079557721, "start": "/Date(1511677631621)/"}]}, {"deviceID": 2, "interactions": [{"duration": 3.962087683065745, "start": "/Date(1511677631621)/"}]}, {"deviceID": 3, "interactions": [{"duration": 3.488720628258253, "start": "/Date(1511677631621)/"}]}, {"deviceID": 4, "interactions": [{"duration": 4.7225037059319686, "start": "/Date(1511677631621)/"}]}, {"deviceID": 5, "interactions": [{"duration": 6.362582770684098, "start": "/Date(1511677631621)/"}]}, {"deviceID": 6, "interactions": [{"duration": 4.675717327776588, "start": "/Date(1511677631621)/"}]}, {"deviceID": 7, "interactions": [{"duration": 5.6899596767847544, "start": "/Date(1511677631621)/"}]}, {"deviceID": 8, "interactions": [{"duration": 2.9923410612872123, "start": "/Date(1511677631621)/"}]}, {"deviceID": 9, "interactions": [{"duration": 3.0826284257372416, "start": "/Date(1511677631621)/"}]}, {"deviceID": 10, "interactions": [{"duration": 5.63727942108547, "start": "/Date(1511677631621)/"}]}, {"deviceID": 11, "interactions": [{"duration": 2.2218547272041533, "start": "/Date(1511677631621)/"}]}, {"deviceID": 12, "interactions": [{"duration": 3.3005285963147495, "start": "/Date(1511677631621)/"}]}, {"deviceID": 13, "interactions": [{"duration": 2.993823462727501, "start": "/Date(1511677631621)/"}]}, {"deviceID": 14, "interactions": [{"duration": 4.554257227379159, "start": "/Date(1511677631621)/"}]}, {"deviceID": 15, "interactions": [{"duration": 2.407133500323297, "start": "/Date(1511677631621)/"}]}, {"deviceID": 16, "interactions": [{"duration": 2.9326089773674737, "start": "/Date(1511677631621)/"}]}, {"deviceID": 17, "interactions": [{"duration": 2.0358050498839604, "start": "/Date(1511677631621)/"}]}, {"deviceID": 18, "interactions": [{"duration": 2.7278682808631585, "start": "/Date(1511677631621)/"}]}, {"deviceID": 19, "interactions": [{"duration": 6.456377397232383, "start": "/Date(1511677631621)/"}]}, {"deviceID": 20, "interactions": [{"duration": 1.1832595069556404, "start": "/Date(1511677631621)/"}]}, {"deviceID": 21, "interactions": [{"duration": 4.5818771699061385, "start": "/Date(1511677631621)/"}]}, {"deviceID": 22, "interactions": [{"duration": 5.368959600847427, "start": "/Date(1511677631621)/"}]}, {"deviceID": 24, "interactions": [{"duration": 1.372210287788262, "start": "/Date(1511677631621)/"}]}, {"deviceID": 25, "interactions": [{"duration": 4.035143649416715, "start": "/Date(1511677631621)/"}]}, {"deviceID": 26, "interactions": [{"duration": 1.2545195528491229, "start": "/Date(1511677631621)/"}]}, {"deviceID": 27, "interactions": [{"duration": 2.240258171714306, "start": "/Date(1511677631621)/"}]}, {"deviceID": 28, "interactions": [{"duration": 3.756521867768884, "start": "/Date(1511677631621)/"}]}, {"deviceID": 30, "interactions": [{"duration": 3.698426250002557, "start": "/Date(1511677631621)/"}]}, {"deviceID": 31, "interactions": [{"duration": 1.180825846821353, "start": "/Date(1511677631621)/"}]}, {"deviceID": 0, "interactions": [{"duration": 2.7069801292738207, "start": "/Date(1511677632195)/"}]}, {"deviceID": 1, "interactions": [{"duration": 7.589443497309457, "start": "/Date(1511677632195)/"}]}, {"deviceID": 2, "interactions": [{"duration": 3.4291861897372744, "start": "/Date(1511677632195)/"}]}, {"deviceID": 3, "interactions": [{"duration": 3.8615263092458343, "start": "/Date(1511677632195)/"}]}, {"deviceID": 4, "interactions": [{"duration": 4.399777455054816, "start": "/Date(1511677632195)/"}]}, {"deviceID": 5, "interactions": [{"duration": 5.905766637338073, "start": "/Date(1511677632195)/"}]}, {"deviceID": 7, "interactions": [{"duration": 4.582423116551093, "start": "/Date(1511677632195)/"}]}, {"deviceID": 8, "interactions": [{"duration": 2.6971775302886747, "start": "/Date(1511677632195)/"}]}, {"deviceID": 9, "interactions": [{"duration": 3.1973643754564787, "start": "/Date(1511677632195)/"}]}, {"deviceID": 10, "interactions": [{"duration": 5.267959790425031, "start": "/Date(1511677632195)/"}]}, {"deviceID": 11, "interactions": [{"duration": 2.1146894785886468, "start": "/Date(1511677632195)/"}]}, {"deviceID": 12, "interactions": [{"duration": 3.723754867255899, "start": "/Date(1511677632195)/"}]}, {"deviceID": 13, "interactions": [{"duration": 3.0272973571933433, "start": "/Date(1511677632195)/"}]}, {"deviceID": 14, "interactions": [{"duration": 4.66441694245946, "start": "/Date(1511677632195)/"}]}, {"deviceID": 15, "interactions": [{"duration": 1.8432940917819252, "start": "/Date(1511677632195)/"}]}, {"deviceID": 16, "interactions": [{"duration": 3.472580612325382, "start": "/Date(1511677632195)/"}]}, {"deviceID": 17, "interactions": [{"duration": 3.7154434724979604, "start": "/Date(1511677632195)/"}]}, {"deviceID": 18, "interactions": [{"duration": 3.4708438250474143, "start": "/Date(1511677632195)/"}]}, {"deviceID": 20, "interactions": [{"duration": 1.4615787074174724, "start": "/Date(1511677632195)/"}]}, {"deviceID": 21, "interactions": [{"duration": 3.032952748255923, "start": "/Date(1511677632195)/"}]}, {"deviceID": 22, "interactions": [{"duration": 4.847368790452667, "start": "/Date(1511677632195)/"}]}, {"deviceID": 23, "interactions": [{"duration": 5.641804945031258, "start": "/Date(1511677632195)/"}]}, {"deviceID": 24, "interactions": [{"duration": 1.2277306294465522, "start": "/Date(1511677632195)/"}]}, {"deviceID": 25, "interactions": [{"duration": 2.6182030358339716, "start": "/Date(1511677632195)/"}]}, {"deviceID": 26, "interactions": [{"duration": 1.476983440048245, "start": "/Date(1511677632195)/"}]}, {"deviceID": 27, "interactions": [{"duration": 2.544153505454357, "start": "/Date(1511677632195)/"}]}, {"deviceID": 28, "interactions": [{"duration": 2.338085862135669, "start": "/Date(1511677632195)/"}]}, {"deviceID": 29, "interactions": [{"duration": 3.1048726007944616, "start": "/Date(1511677632195)/"}]}, {"deviceID": 31, "interactions": [{"duration": 2.4090879157211633, "start": "/Date(1511677632195)/"}]}, {"deviceID": 0, "interactions": [{"duration": 2.3637054051565625, "start": "/Date(1511677632773)/"}]}, {"deviceID": 1, "interactions": [{"duration": 6.857215745893834, "start": "/Date(1511677632773)/"}]}, {"deviceID": 2, "interactions": [{"duration": 3.587163534310477, "start": "/Date(1511677632773)/"}]}, {"deviceID": 3, "interactions": [{"duration": 4.307850634054586, "start": "/Date(1511677632773)/"}]}, {"deviceID": 4, "interactions": [{"duration": 3.3942271153439396, "start": "/Date(1511677632773)/"}]}, {"deviceID": 5, "interactions": [{"duration": 6.427084206500329, "start": "/Date(1511677632773)/"}]}, {"deviceID": 6, "interactions": [{"duration": 5.4879953050574715, "start": "/Date(1511677632773)/"}]}, {"deviceID": 9, "interactions": [{"duration": 3.3652718897904803, "start": "/Date(1511677632773)/"}]}, {"deviceID": 10, "interactions": [{"duration": 5.14520510076074, "start": "/Date(1511677632773)/"}]}, {"deviceID": 11, "interactions": [{"duration": 1.1388247348874296, "start": "/Date(1511677632773)/"}]}, {"deviceID": 12, "interactions": [{"duration": 3.158008202140291, "start": "/Date(1511677632773)/"}]}, {"deviceID": 13, "interactions": [{"duration": 3.332408385786469, "start": "/Date(1511677632773)/"}]}, {"deviceID": 14, "interactions": [{"duration": 4.063702203236961, "start": "/Date(1511677632773)/"}]}, {"deviceID": 15, "interactions": [{"duration": 0.6496776986025405, "start": "/Date(1511677632773)/"}]}, {"deviceID": 16, "interactions": [{"duration": 3.069299064660157, "start": "/Date(1511677632773)/"}]}, {"deviceID": 17, "interactions": [{"duration": 3.246688543099375, "start": "/Date(1511677632773)/"}]}, {"deviceID": 18, "interactions": [{"duration": 2.394375139415312, "start": "/Date(1511677632773)/"}]}, {"deviceID": 19, "interactions": [{"duration": 5.647314232808698, "start": "/Date(1511677632773)/"}]}, {"deviceID": 21, "interactions": [{"duration": 4.339466202591642, "start": "/Date(1511677632773)/"}]}, {"deviceID": 22, "interactions": [{"duration": 4.967875389499354, "start": "/Date(1511677632773)/"}]}, {"deviceID": 23, "interactions": [{"duration": 4.541762330279055, "start": "/Date(1511677632773)/"}]}, {"deviceID": 24, "interactions": [{"duration": 0.7424877529038982, "start": "/Date(1511677632773)/"}]}, {"deviceID": 25, "interactions": [{"duration": 2.2966810153277137, "start": "/Date(1511677632773)/"}]}, {"deviceID": 26, "interactions": [{"duration": 2.6972022932444464, "start": "/Date(1511677632773)/"}]}, {"deviceID": 27, "interactions": [{"duration": 2.4544342406878363, "start": "/Date(1511677632773)/"}]}, {"deviceID": 28, "interactions": [{"duration": 2.3561459704464083, "start": "/Date(1511677632773)/"}]}, {"deviceID": 29, "interactions": [{"duration": 3.120048890059864, "start": "/Date(1511677632773)/"}]}, {"deviceID": 30, "interactions": [{"duration": 3.7341594284127693, "start": "/Date(1511677632773)/"}]}, {"deviceID": 31, "interactions": [{"duration": 1.3290502611886377, "start": "/Date(1511677632773)/"}]}, {"deviceID": 0, "interactions": [{"duration": 1.9615247093288668, "start": "/Date(1511677633349)/"}]}, {"deviceID": 1, "interactions": [{"duration": 7.071837920787845, "start": "/Date(1511677633349)/"}]}, {"deviceID": 2, "interactions": [{"duration": 3.5035936385886495, "start": "/Date(1511677633349)/"}]}, {"deviceID": 3, "interactions": [{"duration": 4.093365488962025, "start": "/Date(1511677633349)/"}]}, {"deviceID": 4, "interactions": [{"duration": 3.8781268243032665, "start": "/Date(1511677633349)/"}]}, {"deviceID": 5, "interactions": [{"duration": 5.7981144882269815, "start": "/Date(1511677633349)/"}]}, {"deviceID": 6, "interactions": [{"duration": 4.148647562177281, "start": "/Date(1511677633349)/"}]}, {"deviceID": 7, "interactions": [{"duration": 4.905168371862937, "start": "/Date(1511677633349)/"}]}, {"deviceID": 8, "interactions": [{"duration": 2.276748829689895, "start": "/Date(1511677633349)/"}]}, {"deviceID": 9, "interactions": [{"duration": 3.4376058753561525, "start": "/Date(1511677633349)/"}]}, {"deviceID": 10, "interactions": [{"duration": 4.761083343962454, "start": "/Date(1511677633349)/"}]}, {"deviceID": 12, "interactions": [{"duration": 2.688077352716131, "start": "/Date(1511677633349)/"}]}, {"deviceID": 13, "interactions": [{"duration": 3.318646665539074, "start": "/Date(1511677633349)/"}]}, {"deviceID": 15, "interactions": [{"duration": 2.3606138185045658, "start": "/Date(1511677633349)/"}]}, {"deviceID": 16, "interactions": [{"duration": 3.4245737418452746, "start": "/Date(1511677633349)/"}]}, {"deviceID": 17, "interactions": [{"duration": 2.72162285245054, "start": "/Date(1511677633349)/"}]}, {"deviceID": 18, "interactions": [{"duration": 2.9238742319452684, "start": "/Date(1511677633349)/"}]}, {"deviceID": 19, "interactions": [{"duration": 6.452122625908233, "start": "/Date(1511677633349)/"}]}, {"deviceID": 20, "interactions": [{"duration": 2.6279009202589947, "start": "/Date(1511677633349)/"}]}, {"deviceID": 21, "interactions": [{"duration": 4.197008671299932, "start": "/Date(1511677633349)/"}]}, {"deviceID": 22, "interactions": [{"duration": 4.4336695598061375, "start": "/Date(1511677633349)/"}]}, {"deviceID": 23, "interactions": [{"duration": 4.830592011033682, "start": "/Date(1511677633349)/"}]}, {"deviceID": 24, "interactions": [{"duration": 0.9842736349975234, "start": "/Date(1511677633349)/"}]}, {"deviceID": 25, "interactions": [{"duration": 2.8188588138660293, "start": "/Date(1511677633349)/"}]}, {"deviceID": 26, "interactions": [{"duration": 1.8557419197997258, "start": "/Date(1511677633349)/"}]}, {"deviceID": 27, "interactions": [{"duration": 2.4694430345183447, "start": "/Date(1511677633349)/"}]}, {"deviceID": 28, "interactions": [{"duration": 3.5549702119907796, "start": "/Date(1511677633349)/"}]}, {"deviceID": 29, "interactions": [{"duration": 2.8581887265829424, "start": "/Date(1511677633349)/"}]}, {"deviceID": 30, "interactions": [{"duration": 4.3193011884944825, "start": "/Date(1511677633349)/"}]}, {"deviceID": 31, "interactions": [{"duration": 1.7924922498278157, "start": "/Date(1511677633349)/"}]}, {"deviceID": 0, "interactions": [{"duration": 2.7464461674352334, "start": "/Date(1511677633957)/"}]}, {"deviceID": 1, "interactions": [{"duration": 7.287547364580363, "start": "/Date(1511677633957)/"}]}, {"deviceID": 2, "interactions": [{"duration": 2.8137376737799826, "start": "/Date(1511677633957)/"}]}, {"deviceID": 3, "interactions": [{"duration": 4.673864641053543, "start": "/Date(1511677633957)/"}]}, {"deviceID": 5, "interactions": [{"duration": 6.849053455322403, "start": "/Date(1511677633957)/"}]}, {"deviceID": 6, "interactions": [{"duration": 5.800609292898978, "start": "/Date(1511677633957)/"}]}, {"deviceID": 7, "interactions": [{"duration": 4.317637289148806, "start": "/Date(1511677633957)/"}]}, {"deviceID": 8, "interactions": [{"duration": 2.5096174246754366, "start": "/Date(1511677633957)/"}]}, {"deviceID": 9, "interactions": [{"duration": 2.749503047520278, "start": "/Date(1511677633957)/"}]}, {"deviceID": 10, "interactions": [{"duration": 5.1673916485359275, "start": "/Date(1511677633957)/"}]}, {"deviceID": 11, "interactions": [{"duration": 2.0943692565101455, "start": "/Date(1511677633957)/"}]}, {"deviceID": 12, "interactions": [{"duration": 2.637500471772736, "start": "/Date(1511677633957)/"}]}, {"deviceID": 13, "interactions": [{"duration": 2.6822122971561733, "start": "/Date(1511677633957)/"}]}, {"deviceID": 14, "interactions": [{"duration": 5.231567806722719, "start": "/Date(1511677633957)/"}]}, {"deviceID": 15, "interactions": [{"duration": 1.6131384513667333, "start": "/Date(1511677633957)/"}]}, {"deviceID": 17, "interactions": [{"duration": 2.9635587412347344, "start": "/Date(1511677633957)/"}]}, {"deviceID": 18, "interactions": [{"duration": 3.9936868836157795, "start": "/Date(1511677633957)/"}]}, {"deviceID": 19, "interactions": [{"duration": 6.501511734207654, "start": "/Date(1511677633957)/"}]}, {"deviceID": 20, "interactions": [{"duration": 2.7488500970852043, "start": "/Date(1511677633957)/"}]}, {"deviceID": 21, "interactions": [{"duration": 3.8943838654335425, "start": "/Date(1511677633957)/"}]}, {"deviceID": 22, "interactions": [{"duration": 4.4405487794395535, "start": "/Date(1511677633957)/"}]}, {"deviceID": 23, "interactions": [{"duration": 5.217731930858157, "start": "/Date(1511677633957)/"}]}, {"deviceID": 24, "interactions": [{"duration": 1.3470597553951842, "start": "/Date(1511677633957)/"}]}, {"deviceID": 25, "interactions": [{"duration": 3.0732072363146483, "start": "/Date(1511677633957)/"}]}, {"deviceID": 26, "interactions": [{"duration": 2.486005958478783, "start": "/Date(1511677633957)/"}]}, {"deviceID": 27, "interactions": [{"duration": 3.058460395930925, "start": "/Date(1511677633957)/"}]}, {"deviceID": 28, "interactions": [{"duration": 2.9284393710083174, "start": "/Date(1511677633957)/"}]}, {"deviceID": 29, "interactions": [{"duration": 3.457722722308359, "start": "/Date(1511677633957)/"}]}, {"deviceID": 30, "interactions": [{"duration": 4.230395967776168, "start": "/Date(1511677633957)/"}]}, {"deviceID": 31, "interactions": [{"duration": 1.8118956385930334, "start": "/Date(1511677633957)/"}]}, {"deviceID": 0, "interactions": [{"duration": 1.9442485325170207, "start": "/Date(1511677634534)/"}]}, {"deviceID": 1, "interactions": [{"duration": 6.691846526200277, "start": "/Date(1511677634534)/"}]}, {"deviceID": 2, "interactions": [{"duration": 4.2147301484297035, "start": "/Date(1511677634534)/"}]}, {"deviceID": 3, "interactions": [{"duration": 3.8689686777318077, "start": "/Date(1511677634534)/"}]}, {"deviceID": 4, "interactions": [{"duration": 4.420865483097328, "start": "/Date(1511677634534)/"}]}, {"deviceID": 5, "interactions": [{"duration": 6.53540292979614, "start": "/Date(1511677634534)/"}]}, {"deviceID": 6, "interactions": [{"duration": 5.093957761368659, "start": "/Date(1511677634534)/"}]}, {"deviceID": 7, "interactions": [{"duration": 4.613145269719999, "start": "/Date(1511677634534)/"}]}, {"deviceID": 9, "interactions": [{"duration": 3.141773681684254, "start": "/Date(1511677634534)/"}]}, {"deviceID": 10, "interactions": [{"duration": 5.074302521668671, "start": "/Date(1511677634534)/"}]}, {"deviceID": 11, "interactions": [{"duration": 1.980335036241974, "start": "/Date(1511677634534)/"}]}, {"deviceID": 12, "interactions": [{"duration": 3.296735031063868, "start": "/Date(1511677634534)/"}]}, {"deviceID": 13, "interactions": [{"duration": 3.013656441781202, "start": "/Date(1511677634534)/"}]}, {"deviceID": 14, "interactions": [{"duration": 4.4370842049773, "start": "/Date(1511677634534)/"}]}, {"deviceID": 15, "interactions": [{"duration": 0.3331948454364386, "start": "/Date(1511677634534)/"}]}, {"deviceID": 17, "interactions": [{"duration": 2.815532892870624, "start": "/Date(1511677634534)/"}]}, {"deviceID": 18, "interactions": [{"duration": 3.4793634749987605, "start": "/Date(1511677634534)/"}]}, {"deviceID": 19, "interactions": [{"duration": 6.5638024785511595, "start": "/Date(1511677634534)/"}]}, {"deviceID": 20, "interactions": [{"duration": 2.082497900866883, "start": "/Date(1511677634534)/"}]}, {"deviceID": 21, "interactions": [{"duration": 3.550409836940244, "start": "/Date(1511677634534)/"}]}, {"deviceID": 22, "interactions": [{"duration": 5.239568211212695, "start": "/Date(1511677634534)/"}]}, {"deviceID": 23, "interactions": [{"duration": 4.535444537096052, "start": "/Date(1511677634534)/"}]}, {"deviceID": 24, "interactions": [{"duration": 1.390235912261057, "start": "/Date(1511677634534)/"}]}, {"deviceID": 26, "interactions": [{"duration": 1.9963228022073765, "start": "/Date(1511677634534)/"}]}, {"deviceID": 28, "interactions": [{"duration": 2.9490558293679494, "start": "/Date(1511677634534)/"}]}]